lerobot_teleoperator_yam_gello/__init__.py
lerobot_teleoperator_yam_gello/config_yam_leader.py
lerobot_teleoperator_yam_gello/yam_leader.py
lerobot_teleoperator_yam_gello-0.1.1.dist-info/METADATA
lerobot_teleoperator_yam_gello-0.1.1.dist-info/WHEEL
lerobot_teleoperator_yam_gello-0.1.1.dist-info/top_level.txt
lerobot_teleoperator_yam_gello-0.1.1.dist-info/RECORD
